mablars/__init__.py
mablars/dataloaders.py
mablars/mablar.py
mablars/mablar_cd.py
mablars/membership_functions.py
mablars-0.1.8.dist-info/LICENSE
mablars-0.1.8.dist-info/METADATA
mablars-0.1.8.dist-info/WHEEL
mablars-0.1.8.dist-info/top_level.txt
mablars-0.1.8.dist-info/RECORD
