Metadata-Version: 2.1
Name: mablars
Version: 0.1.8
Summary: This is a python package of mablars
Home-page: https://github.com/ztcsrookie/mablars
Author: Te Zhang
Author-email: ztcsrookie@gmail.com
Classifier: Programming Language :: Python :: 3.8
Classifier: License :: OSI Approved :: MIT License
Classifier: Operating System :: MacOS :: MacOS X
License-File: LICENSE
Requires-Dist: numpy
Requires-Dist: matplotlib
Requires-Dist: causal-learn
Requires-Dist: scikit-learn
Requires-Dist: python-weka-wrapper3
